mopidy_tubeify/__init__.py
mopidy_tubeify/allmusic.py
mopidy_tubeify/amrap.py
mopidy_tubeify/apple.py
mopidy_tubeify/backend.py
mopidy_tubeify/data.py
mopidy_tubeify/ext.conf
mopidy_tubeify/pitchfork.py
mopidy_tubeify/serviceclient.py
mopidy_tubeify/spotify.py
mopidy_tubeify/tidal.py
mopidy_tubeify/tripler.py
mopidy_tubeify/yt_matcher.py
Mopidy_Tubeify-0.1.0.dist-info/LICENSE
Mopidy_Tubeify-0.1.0.dist-info/METADATA
Mopidy_Tubeify-0.1.0.dist-info/WHEEL
Mopidy_Tubeify-0.1.0.dist-info/entry_points.txt
Mopidy_Tubeify-0.1.0.dist-info/top_level.txt
Mopidy_Tubeify-0.1.0.dist-info/RECORD
